howzat/__init__.py
howzat/howzat.cpython-311-darwin.so
howzat-0.2.0.post1.dist-info/METADATA
howzat-0.2.0.post1.dist-info/WHEEL
howzat-0.2.0.post1.dist-info/licenses/LICENSE
howzat-0.2.0.post1.dist-info/RECORD
