Metadata-Version: 2.4
Name: howzat
Version: 0.2.0.post1
Classifier: License :: OSI Approved :: GNU Affero General Public License v3
Classifier: Programming Language :: Python :: 3
Classifier: Programming Language :: Rust
Classifier: Operating System :: OS Independent
Requires-Dist: numpy>=1.23
License-File: LICENSE
Summary: High-performance polytope backends via Rust FFI bindings to howzat
Requires-Python: >=3.10
